fastmessage/__init__.py
fastmessage/callable_wrapper.py
fastmessage/common.py
fastmessage/exceptions.py
fastmessage/fastmessage_handler.py
fastmessage/method_validator.py
fastmessage/py.typed
fastmessage-0.2.1.dist-info/LICENSE
fastmessage-0.2.1.dist-info/METADATA
fastmessage-0.2.1.dist-info/WHEEL
fastmessage-0.2.1.dist-info/top_level.txt
fastmessage-0.2.1.dist-info/RECORD
