Metadata-Version: 2.1
Name: fastmessage
Version: 0.2.1
Author-email: Aviv Salem <avivsalem@gmail.com>
Maintainer-email: Aviv Salem <avivsalem@gmail.com>
License: MIT
Project-URL: Homepage, https://github.com/Avivsalem/FastMessage/
Project-URL: Documentation, https://fastmessage.readthedocs.io/
Platform: win32
Platform: linux
Classifier: Programming Language :: Python
Classifier: Programming Language :: Python :: 3.7
Classifier: Programming Language :: Python :: 3.8
Classifier: Programming Language :: Python :: 3.9
Classifier: Programming Language :: Python :: 3.10
Classifier: Programming Language :: Python :: 3.11
Classifier: License :: OSI Approved :: MIT License
Requires-Python: <3.12,>=3.7
License-File: LICENSE
Requires-Dist: messageflux <1,>=0.5.0
Requires-Dist: pydantic <2,>=1.10.1
Provides-Extra: all
Requires-Dist: flake8 ; extra == 'all'
Requires-Dist: lxml ; extra == 'all'
Requires-Dist: mock ; extra == 'all'
Requires-Dist: mypy ; extra == 'all'
Requires-Dist: pytest ; extra == 'all'
Requires-Dist: pytest-cov ; extra == 'all'
Requires-Dist: tox ; extra == 'all'
Provides-Extra: dev
Requires-Dist: pytest ; extra == 'dev'
Requires-Dist: pytest-cov ; extra == 'dev'
Requires-Dist: mock ; extra == 'dev'
Requires-Dist: mypy ; extra == 'dev'
Requires-Dist: lxml ; extra == 'dev'
Requires-Dist: flake8 ; extra == 'dev'
Requires-Dist: tox ; extra == 'dev'
